{
    "principal_primitives": [
        {
            "type": "cylinder",
            "param": {
                "L1": 183,
                "L2": 255,
                "Q_0": 128,
                "Q_1": 256,
                "Q_2": 128,
                "Q_3": 128,
                "T_x": 128,
                "T_y": 128,
                "T_z": 128
            }
        }
    ],
    "detail_features": [
        {
            "type": "rect_psg",
            "param": {
                "len": 83,
                "wid": 83,
                "x1": 129,
                "x2": 129,
                "y1": 129,
                "y2": 129,
                "z1": 0,
                "z2": 256
            }
        }
    ]
}